{"cameraMode":{"drawMode":0,"name":"Shaded","section":"Shading Mode"},"sceneLighting":false,"audioPlay":false,"sceneViewState":{"showFog":true,"showMaterialUpdate":false,"showSkybox":false,"showFlares":true,"showImageEffects":true,"showParticleSystems":true},"in2DMode":false,"pivot":{"x":-47.532020568847659,"y":3.0224647521972658,"z":-94.22045135498047},"rotation":{"x":0.01216522604227066,"y":0.9865178465843201,"z":0.13820770382881165,"w":-0.08684858679771424},"size":6.996608257293701,"orthographic":false}